{
	"textures": {
		"0": "ssbrc:blueprint/booth/clone_ridley/texture",
		"particle": "minecraft:item/pufferfish"
	},
	"display": {
		"head": {
			"rotation": [0, 180, 0]
		}
	},
	"elements": [
		{
			"from": [-8.26547, 18.45441, -16],
			"to": [-7.49174, 19.2744, -8.97198],
			"rotation": {
				"x": 0,
				"y": 0,
				"z": 0,
				"origin": [8, 8, 8]
			},
			"faces": {
				"north": {
					"uv": [0.9375, 2.25, 0.875, 2.3125],
					"texture": "#0"
				},
				"east": {
					"uv": [1.8125, 2.25, 0.9375, 2.3125],
					"texture": "#0"
				},
				"south": {
					"uv": [1.875, 2.25, 1.8125, 2.3125],
					"texture": "#0"
				},
				"west": {
					"uv": [0.875, 2.25, 0, 2.3125],
					"texture": "#0"
				},
				"up": {
					"uv": [0.875, 2.25, 0.9375, 1.375],
					"texture": "#0"
				},
				"down": {
					"uv": [0.9375, 1.375, 1, 2.25],
					"texture": "#0"
				}
			}
		}
	]
}
